hebspacy/__init__.py
hebspacy/ner_head.py
hebspacy/version.py
tests/__init__.py
tests/conftest.py
tests/test_consolidator.py
tests/test_ner_head.py
hebspacy-0.1.7.dist-info/LICENSE
hebspacy-0.1.7.dist-info/METADATA
hebspacy-0.1.7.dist-info/WHEEL
hebspacy-0.1.7.dist-info/entry_points.txt
hebspacy-0.1.7.dist-info/top_level.txt
hebspacy-0.1.7.dist-info/RECORD
