Metadata-Version: 2.1
Name: hebspacy
Version: 0.1.7
Summary: SpaCy pipeline and models for Hebrew text
Home-page: https://github.com/8400TheHealthNetwork/HebSpacy
Author: hebpsacy
Author-email: hebspacy@gmail.com
License: MIT License (MIT)
Keywords: hebrew nlp spacy SpaCy phi pii
Platform: UNKNOWN
Requires-Python: >=3.8.0
License-File: LICENSE
Requires-Dist: sentencepiece (==0.1.96)
Requires-Dist: spacy-transformers
Requires-Dist: spacy (==3.2.2)
Requires-Dist: tokenizers
Requires-Dist: torch
Requires-Dist: transformers
